federa/__init__.py
federa/client/__init__.py
federa/client/start_client.py
federa/client/src/ClientConnection_pb2.py
federa/client/src/ClientConnection_pb2_grpc.py
federa/client/src/__init__.py
federa/client/src/client.py
federa/client/src/client_lib.py
federa/client/src/data_utils.py
federa/client/src/distribution.py
federa/client/src/get_data.py
federa/client/src/net.py
federa/client/src/net_lib.py
federa/server/__init__.py
federa/server/start_server.py
federa/server/src/ClientConnection_pb2.py
federa/server/src/ClientConnection_pb2_grpc.py
federa/server/src/__init__.py
federa/server/src/client_connection_servicer.py
federa/server/src/client_manager.py
federa/server/src/client_wrapper.py
federa/server/src/server.py
federa/server/src/server_lib.py
federa/server/src/verification.py
federa/server/src/algorithms/fedadagrad.py
federa/server/src/algorithms/fedadam.py
federa/server/src/algorithms/fedavg.py
federa/server/src/algorithms/fedavgm.py
federa/server/src/algorithms/feddyn.py
federa/server/src/algorithms/fedyogi.py
federa/server/src/algorithms/mime.py
federa/server/src/algorithms/mimelite.py
federa/server/src/algorithms/scaffold.py
federa/server/src/server_evaluate/__init__.py
federa/server/src/server_evaluate/eval_lib.py
federa/tests/minitest.json
federa/tests/minitest.py
federa/tests/misc.py
federa-1.0.0.dist-info/METADATA
federa-1.0.0.dist-info/WHEEL
federa-1.0.0.dist-info/licenses/LICENSE
federa-1.0.0.dist-info/RECORD
