Metadata-Version: 2.1
Name: federa
Version: 1.0.0
Summary: FedERA is a highly dynamic and customizable framework that can accommodate many use cases with flexibility by implementing several functionalities over different federated learning algorithms, and essentially creating a plug-and-play architecture to accommodate different use cases.
Project-URL: Homepage, https://github.com/anupamkliv/FedERA
Project-URL: Bug Tracker, https://github.com/anupamkliv/FedERA/issues
Author-email: Anupam Borthakur <anupamborthakur@kgpian.iitkgp.ac.in>
License-File: LICENSE
Classifier: License :: OSI Approved :: Apache Software License
Classifier: Operating System :: OS Independent
Classifier: Programming Language :: Python :: 3
Requires-Python: >=3.7
Requires-Dist: bandit
Requires-Dist: codecarbon==2.1.4
Requires-Dist: grpcio>=1.53.0
Requires-Dist: matplotlib
Requires-Dist: numpy>=1.23.4
Requires-Dist: pillow>=9.5.0
Requires-Dist: protobuf>=3.20.2
Requires-Dist: torch>=2.0.0
Requires-Dist: torchvision>=0.15.1
Requires-Dist: tqdm>=4.65.0
